pypiserver/__init__.py
pypiserver/__main__.py
pypiserver/_app.py
pypiserver/backend.py
pypiserver/cache.py
pypiserver/config.py
pypiserver/core.py
pypiserver/manage.py
pypiserver/pkg_helpers.py
pypiserver/plugin.py
pypiserver/welcome.html
pypiserver/bottle_wrapper/__init__.py
pypiserver/bottle_wrapper/bottle.py
pypiserver-2.4.0.dist-info/licenses/AUTHORS.rst
pypiserver-2.4.0.dist-info/licenses/LICENSE.txt
pypiserver-2.4.0.dist-info/METADATA
pypiserver-2.4.0.dist-info/WHEEL
pypiserver-2.4.0.dist-info/entry_points.txt
pypiserver-2.4.0.dist-info/top_level.txt
pypiserver-2.4.0.dist-info/zip-safe
pypiserver-2.4.0.dist-info/RECORD
