Metadata-Version: 2.4
Name: pypiserver
Version: 2.4.0
Summary: A minimal PyPI server for use with pip/easy_install.
Home-page: https://github.com/pypiserver/pypiserver
Maintainer: Kostis Anagnostopoulos <ankostis@gmail.com>Matthew Planchard <mplanchard@gmail.com>
Maintainer-email: ankostis@gmail.com
Platform: any
Classifier: Development Status :: 5 - Production/Stable
Classifier: Environment :: Web Environment
Classifier: Intended Audience :: Developers
Classifier: Intended Audience :: System Administrators
Classifier: License :: OSI Approved :: BSD License
Classifier: License :: OSI Approved :: zlib/libpng License
Classifier: Operating System :: MacOS :: MacOS X
Classifier: Operating System :: Microsoft :: Windows
Classifier: Operating System :: POSIX
Classifier: Operating System :: OS Independent
Classifier: Programming Language :: Python :: 3
Classifier: Programming Language :: Python :: 3.8
Classifier: Programming Language :: Python :: 3.9
Classifier: Programming Language :: Python :: 3.10
Classifier: Programming Language :: Python :: 3.11
Classifier: Programming Language :: Python :: 3.12
Classifier: Programming Language :: Python :: Implementation :: CPython
Classifier: Programming Language :: Python :: Implementation :: PyPy
Classifier: Topic :: Software Development :: Build Tools
Classifier: Topic :: System :: Software Distribution
Requires-Python: >=3.8
License-File: LICENSE.txt
License-File: AUTHORS.rst
Requires-Dist: pip>=7
Requires-Dist: packaging>=23.2
Requires-Dist: importlib_resources; python_version > "3.8" and python_version < "3.12"
Provides-Extra: passlib
Requires-Dist: passlib>=1.6; extra == "passlib"
Provides-Extra: cache
Requires-Dist: watchdog; extra == "cache"
Dynamic: classifier
Dynamic: description
Dynamic: description-content-type
Dynamic: home-page
Dynamic: license-file
Dynamic: maintainer
Dynamic: maintainer-email
Dynamic: platform
Dynamic: provides-extra
Dynamic: requires-dist
Dynamic: requires-python
Dynamic: summary
